cde_render/__init__.py
cde_render/__main__.py
cde_render/aux_data.py
cde_render/common.py
cde_render/data.py
cde_render/default/__init__.py
cde_render/default/assets/meal_halfmeat1.pdf
cde_render/default/assets/meal_halfmeat2.pdf
cde_render/default/assets/meal_meat.pdf
cde_render/default/assets/meal_special.pdf
cde_render/default/assets/meal_vegan.pdf
cde_render/default/assets/meal_vegetarian.pdf
cde_render/default/assets/nametag_background.pdf
cde_render/default/assets/nametag_guest.pdf
cde_render/default/assets/nametag_minor.pdf
cde_render/default/assets/nametag_orga.pdf
cde_render/default/assets/nametag_vertrauensperson.pdf
cde_render/default/config.toml
cde_render/default/targets.py
cde_render/default/templates/_base.override.tex
cde_render/default/templates/_base.tex
cde_render/default/templates/_lists.base.override.tex
cde_render/default/templates/_lists.base.tex
cde_render/default/templates/checklist_arrival.tex
cde_render/default/templates/checklist_departure.tex
cde_render/default/templates/checklist_minors.tex
cde_render/default/templates/donation_receipt.tex
cde_render/default/templates/envelopes.tex
cde_render/default/templates/list_courses.tex
cde_render/default/templates/list_departure.tex
cde_render/default/templates/list_participants.tex
cde_render/default/templates/list_room_changes.tex
cde_render/default/templates/lists_attendees.tex
cde_render/default/templates/lists_rooms.tex
cde_render/default/templates/minor_nightlog.tex
cde_render/default/templates/nametags.tex
cde_render/default/templates/nametags_departure.tex
cde_render/default/templates/orga_list_birthdays.tex
cde_render/default/templates/orga_list_participants.tex
cde_render/default/templates/orga_list_vertrauenspersonen.tex
cde_render/default/templates/overrides/_base.override.tex
cde_render/default/templates/overrides/_lists.base.override.tex
cde_render/default/templates/overrides/_override.txt
cde_render/default/templates/participation_letter.tex
cde_render-4.4.0.dist-info/WHEEL
cde_render-4.4.0.dist-info/entry_points.txt
cde_render-4.4.0.dist-info/METADATA
cde_render-4.4.0.dist-info/RECORD
