Metadata-Version: 2.3
Name: cde-render
Version: 4.4.0
Summary: CdE Event Template Renderer -- A python script to render LaTeX based documents for CdE events via configurable, extendable templates.
Author: Michael Thies
Author-email: Michael Thies <mail@mhthies.de>
License: 
Requires-Dist: jinja2>=3.1.6
Requires-Dist: pytz>=2025.2
Requires-Dist: toml>=0.10.2 ; python_full_version < '3.11'
Requires-Dist: requests>=2.32.3
Requires-Dist: typing-extensions>=4.13.2
Requires-Dist: phonenumbers>=9.0.5
Requires-Dist: pyicu>=2.15.2 ; extra == 'icu'
Maintainer: Tobias Udtke
Maintainer-email: Tobias Udtke <tobias.udtke@gmail.com>
Requires-Python: >=3.10
Project-URL: repository, https://tracker.cde-ev.de/orgas/cde_render
Provides-Extra: icu
